{"rawdatum":{"values":[{"feature":"melaa","area":"bay-of-plenty","values":[80,1.07238605898,null,100],"formatted":["80.0 %","1.07",null,"100.00"],"year":"2011","type":"2011"},{"feature":"melaa","area":"bay-of-plenty","values":[84.6,1.08184143222,4.6,105.75],"formatted":["84.6 %","1.08","4.6 pp","105.75"],"year":"2012","type":"2012"},{"feature":"melaa","area":"bay-of-plenty","values":[89.7,1.15891472868,5.1,112.125],"formatted":["89.7 %","1.16","5.1 pp","112.13"],"year":"2013","type":"2013"},{"feature":"melaa","area":"bay-of-plenty","values":[96.7,1.21026282853,7,120.875],"formatted":["96.7 %","1.21","7.0 pp","120.88"],"year":"2014","type":"2014"},{"feature":"melaa","area":"bay-of-plenty","values":[97.1,1.1769,0.4,121.375],"formatted":["97.1 %","1.18","0.4 pp","121.38"],"year":"2015","type":"2015"},{"feature":"melaa","area":"bay-of-plenty","values":[91.2,1.11764705882,-5.9,114],"formatted":["91.2 %","1.12","-5.9 pp","114.00"],"year":"2016","type":"2016"}],"transforms":["original","ratio-nz","difference","indexed"],"id":"by-ethnicity-ncea-level-2-attainment-rates-for-18-year-olds-bay-of-plenty-melaa","slice":"by-ethnicity-ncea-level-2-attainment-rates-for-18-year-olds"}}