{"rawdatum":{"values":[{"feature":"financial-and-insurance-services","area":"clutha","values":[108,0.2281802624,null,100,60.84507042253,1.22615803814],"formatted":["108","0.2 %",null,"100.00","60.85","1.2 %"],"year":"2000","type":"2000"},{"feature":"financial-and-insurance-services","area":"clutha","values":[93,0.19662565013,-13.8,86.1,52.991452,1.01772816808],"formatted":["93","0.2 %","-13.9 %","86.11","52.99","1.0 %"],"year":"2001","type":"2001"},{"feature":"financial-and-insurance-services","area":"clutha","values":[99,0.21083567595,6.45161290322,91.6,56.571428,1.05973025048],"formatted":["99","0.2 %","6.5 %","91.67","56.57","1.1 %"],"year":"2002","type":"2002"},{"feature":"financial-and-insurance-services","area":"clutha","values":[78,0.15944073097,-21.21,72.2,44.69914040114,0.83952211817],"formatted":["78","0.2 %","-21.2 %","72.22","44.70","0.8 %"],"year":"2003","type":"2003"},{"feature":"financial-and-insurance-services","area":"clutha","values":[84,0.16546507505,7.692307,77.7,48.27586206896,0.89887640449],"formatted":["84","0.2 %","7.7 %","77.78","48.28","0.9 %"],"year":"2004","type":"2004"},{"feature":"financial-and-insurance-services","area":"clutha","values":[93,0.17494356659,10.714285,86.1,53.75722543352,0.98820529167],"formatted":["93","0.2 %","10.7 %","86.11","53.76","1.0 %"],"year":"2005","type":"2005"},{"feature":"financial-and-insurance-services","area":"clutha","values":[96,0.17361,3.22580645161,88.8,55.81395348837,1.01975780752],"formatted":["96","0.2 %","3.2 %","88.89","55.81","1.0 %"],"year":"2006","type":"2006"},{"feature":"financial-and-insurance-services","area":"clutha","values":[108,0.18106830298,12.5,100,62.79069767441,1.14322006986],"formatted":["108","0.2 %","12.5 %","100.00","62.79","1.1 %"],"year":"2007","type":"2007"},{"feature":"financial-and-insurance-services","area":"clutha","values":[105,0.1703080142,-2.7,97.2,60.69364161849,1.09238451935],"formatted":["105","0.2 %","-2.8 %","97.22","60.69","1.1 %"],"year":"2008","type":"2008"},{"feature":"financial-and-insurance-services","area":"clutha","values":[120,0.19588638589,14.285714,111.1,69.16426512968,1.22624156958],"formatted":["120","0.2 %","14.3 %","111.11","69.16","1.2 %"],"year":"2009","type":"2009"},{"feature":"financial-and-insurance-services","area":"clutha","values":[99,0.16449828024,-17.5,91.6,56.89655172413,1.02293862368],"formatted":["99","0.2 %","-17.5 %","91.67","56.90","1.0 %"],"year":"2010","type":"2010"},{"feature":"financial-and-insurance-services","area":"clutha","values":[99,0.16102273836,0,91.6,56.571428,1.02964118564],"formatted":["99","0.2 %","0.0 %","91.67","56.57","1.0 %"],"year":"2011","type":"2011"},{"feature":"financial-and-insurance-services","area":"clutha","values":[96,0.15259895088,-3.03,88.8,55.49132947976,0.99378881987],"formatted":["96","0.2 %","-3.0 %","88.89","55.49","1.0 %"],"year":"2012","type":"2012"},{"feature":"financial-and-insurance-services","area":"clutha","values":[96,0.14699802471,0,88.8,55.65217391304,1.00946372239],"formatted":["96","0.1 %","0.0 %","88.89","55.65","1.0 %"],"year":"2013","type":"2013"},{"feature":"financial-and-insurance-services","area":"clutha","values":[90,0.13709272037,-6.25,83.3,51.87319884726,0.94876660341],"formatted":["90","0.1 %","-6.3 %","83.33","51.87","0.9 %"],"year":"2014","type":"2014"},{"feature":"financial-and-insurance-services","area":"clutha","values":[99.24521576777,0.15071089194,10.27246196418,91.89371830349,57.0374803263,1.02130344005],"formatted":["99","0.2 %","10.3 %","91.89","57.04","1.0 %"],"year":"2015","type":"2015"}],"transforms":["original","national-percentage","annual-rate","indexed","percapita","feature-percentage"],"id":"employment-estimates-by-industry-ansic06-l1-incl-self-employed-clutha-financial-and-insurance-services","slice":"employment-estimates-by-industry-ansic06-l1-incl-self-employed"}}