{"rawdatum":{"values":[{"feature":"professional-scientific-and-technical-services","area":"auckland","values":[57357,42.75937646769,null,100,477.37827715355,9.73527030536],"formatted":["57,357","42.8 %",null,"100.00","477.38","9.7 %"],"year":"2000","type":"2000"},{"feature":"professional-scientific-and-technical-services","area":"auckland","values":[59955,42.36713234826,4.5295256028,104.5295256028,492.12016744644,9.91383372935],"formatted":["59,955","42.4 %","4.5 %","104.53","492.12","9.9 %"],"year":"2001","type":"2001"},{"feature":"professional-scientific-and-technical-services","area":"auckland","values":[63066,42.88366210399,5.18889166875,109.95344944819,502.197802,10.12888771109],"formatted":["63,066","42.9 %","5.2 %","109.95","502.20","10.1 %"],"year":"2002","type":"2002"},{"feature":"professional-scientific-and-technical-services","area":"auckland","values":[65154,43.05709754163,3.31081723908,113.59380720748,502.11159062885,10.01009398002],"formatted":["65,154","43.1 %","3.3 %","113.59","502.11","10.0 %"],"year":"2003","type":"2003"},{"feature":"professional-scientific-and-technical-services","area":"auckland","values":[68829,43.11135330151,5.64048254903,120.00104607981,519.07239819004,10.10059653525],"formatted":["68,829","43.1 %","5.6 %","120.00","519.07","10.1 %"],"year":"2004","type":"2004"},{"feature":"professional-scientific-and-technical-services","area":"auckland","values":[72303,42.9531277847,5.04729111275,126.05784821381,536.01453035806,10.19013754],"formatted":["72,303","43.0 %","5.0 %","126.06","536.01","10.2 %"],"year":"2005","type":"2005"},{"feature":"professional-scientific-and-technical-services","area":"auckland","values":[78639,42.9109303125,8.76312186216,137.10445106961,572.7530954115,10.7079248366],"formatted":["78,639","42.9 %","8.8 %","137.10","572.75","10.7 %"],"year":"2006","type":"2006"},{"feature":"professional-scientific-and-technical-services","area":"auckland","values":[80400,42.7520857594,2.23934688894,140.17469532925,578.25086306098,10.67971611082],"formatted":["80,400","42.8 %","2.2 %","140.17","578.25","10.7 %"],"year":"2007","type":"2007"},{"feature":"professional-scientific-and-technical-services","area":"auckland","values":[83412,42.97438909411,3.74626865671,145.42601600502,593.46851654215,10.85038380637],"formatted":["83,412","43.0 %","3.7 %","145.43","593.47","10.9 %"],"year":"2008","type":"2008"},{"feature":"professional-scientific-and-technical-services","area":"auckland","values":[83517,42.68868647836,0.12588116817,145.6090799728,587.4446085672,10.93801568467],"formatted":["83,517","42.7 %","0.1 %","145.61","587.44","10.9 %"],"year":"2009","type":"2009"},{"feature":"professional-scientific-and-technical-services","area":"auckland","values":[79038,41.85292856121,-5.36297999209,137.80009414718,549.02750764101,10.71886277365],"formatted":["79,038","41.9 %","-5.4 %","137.80","549.03","10.7 %"],"year":"2010","type":"2010"},{"feature":"professional-scientific-and-technical-services","area":"auckland","values":[81903,41.60849818636,3.62483868518,142.79512526805,561.13318717456,10.9242890469],"formatted":["81,903","41.6 %","3.6 %","142.80","561.13","10.9 %"],"year":"2011","type":"2011"},{"feature":"professional-scientific-and-technical-services","area":"auckland","values":[83682,41.94523390625,2.17208160873,145.89675192217,566.75922790382,10.95192288816],"formatted":["83,682","41.9 %","2.2 %","145.90","566.76","11.0 %"],"year":"2012","type":"2012"},{"feature":"professional-scientific-and-technical-services","area":"auckland","values":[84924,41.67599081326,1.4841901,148.06213714106,568.73828020358,10.90972155313],"formatted":["84,924","41.7 %","1.5 %","148.06","568.74","10.9 %"],"year":"2013","type":"2013"},{"feature":"professional-scientific-and-technical-services","area":"auckland","values":[91305,42.90789640636,7.51377702416,159.18719598305,597.97629183312,11.36864517574],"formatted":["91,305","42.9 %","7.5 %","159.19","597.98","11.4 %"],"year":"2014","type":"2014"},{"feature":"professional-scientific-and-technical-services","area":"auckland","values":[86535.5507147653,41.37133043696,-5.22364523874,150.87182159939,551.21696104697,10.59841116157],"formatted":["86,536","41.4 %","-5.2 %","150.87","551.22","10.6 %"],"year":"2015","type":"2015"}],"transforms":["original","national-percentage","annual-rate","indexed","percapita","feature-percentage"],"id":"employment-estimates-by-industry-ansic06-l1-incl-self-employed-auckland-professional-scientific-and-technical-services","slice":"employment-estimates-by-industry-ansic06-l1-incl-self-employed"}}