{"rawdatum":{"values":[{"feature":"65-plus-age-group","area":"southland","values":[10700,0.94690265486,null,100],"formatted":["$10,700","0.95",null,"100.00"],"year":"2010","type":"2010"},{"feature":"65-plus-age-group","area":"southland","values":[11600,0.928,8.41121495327,108.41121495327],"formatted":["$11,600","0.93","8.4 %","108.41"],"year":"2011","type":"2011"},{"feature":"65-plus-age-group","area":"southland","values":[13000,0.962,12.06896551724,121.4953271028],"formatted":["$13,000","0.96","12.1 %","121.50"],"year":"2012","type":"2012"},{"feature":"65-plus-age-group","area":"southland","values":[12100,0.81756,-6.923076,113.08411214953],"formatted":["$12,100","0.82","-6.9 %","113.08"],"year":"2013","type":"2013"},{"feature":"65-plus-age-group","area":"southland","values":[13200,0.814,9.09,123.3644859813],"formatted":["$13,200","0.81","9.1 %","123.36"],"year":"2014","type":"2014"},{"feature":"65-plus-age-group","area":"southland","values":[13800,0.82634730538,4.54,128.97196261682],"formatted":["$13,800","0.83","4.5 %","128.97"],"year":"2015","type":"2015"},{"feature":"65-plus-age-group","area":"southland","values":[15300,0.8453038674,10.86956521739,142.9906542056],"formatted":["$15,300","0.85","10.9 %","142.99"],"year":"2016","type":"2016"}],"transforms":["original","ratio-nz","annual-rate","indexed"],"id":"median-income-estimates-by-age-group-southland-65-plus-age-group","slice":"median-income-estimates-by-age-group"}}