{"rawdatum":{"values":[{"feature":"not-stated","area":"horowhenua","values":[15.81728954322,0.98123355185,null,100],"formatted":["15.8 %","0.98",null,"100.00"],"year":"2001","type":"2001"},{"feature":"not-stated","area":"horowhenua","values":[14.77931904161,0.91066330025,-1.0379705016,93.43774735378],"formatted":["14.8 %","0.91","-1.0 pp","93.44"],"year":"2006","type":"2006"},{"feature":"not-stated","area":"horowhenua","values":[15.71359923113,1.04133156797,0.93428018952,99.34444955438],"formatted":["15.7 %","1.04","0.9 pp","99.34"],"year":"2013","type":"2013"}],"transforms":["original","ratio-nz","difference","indexed"],"id":"percent-household-with-total-annual-income-horowhenua-not-stated","slice":"percent-household-with-total-annual-income"}}