{"rawdatum":{"values":[{"feature":"reading","area":"mackenzie","values":[82.2,1.06064516129,null,100],"formatted":["82.2 %","1.06",null,"100.00"],"year":"2012","type":"2012"},{"feature":"reading","area":"mackenzie","values":[80.15873015873,1.02029070394,-2.04126984126,97.51670335611],"formatted":["80.2 %","1.02","-2.0 pp","97.52"],"year":"2013","type":"2013"},{"feature":"reading","area":"mackenzie","values":[82.99492385786,1.05818951726,2.83619369913,100.96706065434],"formatted":["83.0 %","1.06","2.8 pp","100.97"],"year":"2014","type":"2014"},{"feature":"reading","area":"mackenzie","values":[81.04265402843,1.0340496905,-1.95226982943,98.59203653094],"formatted":["81.0 %","1.03","-2.0 pp","98.59"],"year":"2015","type":"2015"},{"feature":"reading","area":"mackenzie","values":[80.56206088992,1.02792745849,-0.4805931385,98.00737334541],"formatted":["80.6 %","1.03","-0.5 pp","98.01"],"year":"2016","type":"2016"}],"transforms":["original","ratio-nz","difference","indexed"],"id":"percentage-at-or-above-national-standards-mackenzie-reading","slice":"percentage-at-or-above-national-standards"}}