{"rawdatum":{"values":[{"feature":"fishing-and-aquaculture","area":"christchurch","values":[0.12,0.41379310344,null,100],"formatted":["0.1 %","0.41",null,"100.00"],"year":"2000","type":"2000"},{"feature":"fishing-and-aquaculture","area":"christchurch","values":[9.0e-2,0.31034482758,-3.0e-2,75],"formatted":["0.1 %","0.31","-0.0 pp","75.00"],"year":"2001","type":"2001"},{"feature":"fishing-and-aquaculture","area":"christchurch","values":[0.1,0.37,1.0e-2,83.3],"formatted":["0.1 %","0.37","0.0 pp","83.33"],"year":"2002","type":"2002"},{"feature":"fishing-and-aquaculture","area":"christchurch","values":[0.11,0.55,1.0e-2,91.6],"formatted":["0.1 %","0.55","0.0 pp","91.67"],"year":"2003","type":"2003"},{"feature":"fishing-and-aquaculture","area":"christchurch","values":[8.0e-2,0.4,-3.0e-2,66.6],"formatted":["0.1 %","0.44","-0.0 pp","66.67"],"year":"2004","type":"2004"},{"feature":"fishing-and-aquaculture","area":"christchurch","values":[6.0e-2,0.375,-2.0e-2,50],"formatted":["0.1 %","0.38","-0.0 pp","50.00"],"year":"2005","type":"2005"},{"feature":"fishing-and-aquaculture","area":"christchurch","values":[4.0e-2,0.285714,-2.0e-2,33.3],"formatted":["0.0 %","0.29","-0.0 pp","33.33"],"year":"2006","type":"2006"},{"feature":"fishing-and-aquaculture","area":"christchurch","values":[6.0e-2,0.428571,2.0e-2,50],"formatted":["0.1 %","0.43","0.0 pp","50.00"],"year":"2007","type":"2007"},{"feature":"fishing-and-aquaculture","area":"christchurch","values":[5.0e-2,0.5,-1.0e-2,41.6],"formatted":["0.1 %","0.50","-0.0 pp","41.67"],"year":"2008","type":"2008"},{"feature":"fishing-and-aquaculture","area":"christchurch","values":[6.0e-2,0.428571,1.0e-2,50],"formatted":["0.1 %","0.43","0.0 pp","50.00"],"year":"2009","type":"2009"},{"feature":"fishing-and-aquaculture","area":"christchurch","values":[6.0e-2,0.428571,0,50],"formatted":["0.1 %","0.43","0.0 pp","50.00"],"year":"2010","type":"2010"},{"feature":"fishing-and-aquaculture","area":"christchurch","values":[6.0e-2,0.461538,0,50],"formatted":["0.1 %","0.46","0.0 pp","50.00"],"year":"2011","type":"2011"},{"feature":"fishing-and-aquaculture","area":"christchurch","values":[7.0e-2,0.583,1.0e-2,58.3],"formatted":["0.1 %","0.58","0.0 pp","58.33"],"year":"2012","type":"2012"},{"feature":"fishing-and-aquaculture","area":"christchurch","values":[5.0e-2,0.416,-2.0e-2,41.6],"formatted":["0.1 %","0.42","-0.0 pp","41.67"],"year":"2013","type":"2013"},{"feature":"fishing-and-aquaculture","area":"christchurch","values":[3.0e-2,0.230769,-2.0e-2,25],"formatted":["0.0 %","0.23","-0.0 pp","25.00"],"year":"2014","type":"2014"},{"feature":"fishing-and-aquaculture","area":"christchurch","values":[4.0e-2,0.285714,1.0e-2,33.3],"formatted":["0.0 %","0.29","0.0 pp","33.33"],"year":"2015","type":"2015"}],"transforms":["original","ratio-nz","difference","indexed"],"id":"primary-production-share-of-gdp-by-sector-christchurch-fishing-and-aquaculture","slice":"primary-production-share-of-gdp-by-sector"}}