{"rawdatum":{"values":[{"feature":"below-ncea-level-3","area":"taupo","values":[269,0.78938873727,null,100,79.58579881656,70.052083],"formatted":["269","0.8 %",null,"100.00","79.59","70.1 %"],"year":"2009","type":"2009"},{"feature":"below-ncea-level-3","area":"taupo","values":[254,0.73085112505,-5.57620817843,94.42379182156,74.26900584795,70.94972067039],"formatted":["254","0.7 %","-5.6 %","94.42","74.27","70.9 %"],"year":"2010","type":"2010"},{"feature":"below-ncea-level-3","area":"taupo","values":[310,0.91721403633,22.04724409448,115.24163568773,90.37900874635,70.93821510297],"formatted":["310","0.9 %","22.0 %","115.24","90.38","70.9 %"],"year":"2011","type":"2011"},{"feature":"below-ncea-level-3","area":"taupo","values":[229,0.74954176485,-26.12903225806,85.13011152416,66.18497109826,63.61],"formatted":["229","0.7 %","-26.1 %","85.13","66.18","63.6 %"],"year":"2012","type":"2012"},{"feature":"below-ncea-level-3","area":"taupo","values":[265,0.84475613643,15.72052401746,98.51301115241,76.14942528735,66.41604010025],"formatted":["265","0.8 %","15.7 %","98.51","76.15","66.4 %"],"year":"2013","type":"2013"},{"feature":"below-ncea-level-3","area":"taupo","values":[238,0.81414839393,-10.18867924528,88.47583643122,67.806267,63.46],"formatted":["238","0.8 %","-10.2 %","88.48","67.81","63.5 %"],"year":"2014","type":"2014"},{"feature":"below-ncea-level-3","area":"taupo","values":[259,0.91329031348,8.82352941176,96.28252788104,72.75280898876,67.27],"formatted":["259","0.9 %","8.8 %","96.28","72.75","67.3 %"],"year":"2015","type":"2015"},{"feature":"below-ncea-level-3","area":"taupo","values":[230,0.82087155144,-11.196911,85.50185873605,63.5359116022,59.27835051546],"formatted":["230","0.8 %","-11.2 %","85.50","63.54","59.3 %"],"year":"2016","type":"2016"}],"transforms":["original","national-percentage","annual-rate","indexed","percapita","feature-percentage"],"id":"school-leavers-by-ncea-level-taupo-below-ncea-level-3","slice":"school-leavers-by-ncea-level"}}