{"rawdatum":{"values":[{"feature":null,"area":"carterton","values":[190,0.10510012169,null,100,233.70233],"formatted":["190","0.1 %",null,"100.00","233.70"],"year":"2011","type":"2011"},{"feature":null,"area":"carterton","values":[270,0.14467902689,42.10526315789,142.10526315789,324.90974729241],"formatted":["270","0.1 %","42.1 %","142.11","324.91"],"year":"2012","type":"2012"},{"feature":null,"area":"carterton","values":[280,0.14195183776,3.703,147.36842105263,329.79976442873],"formatted":["280","0.1 %","3.7 %","147.37","329.80"],"year":"2013","type":"2013"},{"feature":null,"area":"carterton","values":[285,0.14875515423,1.7857142,150,328.34101382488],"formatted":["285","0.1 %","1.8 %","150.00","328.34"],"year":"2014","type":"2014"},{"feature":null,"area":"carterton","values":[215,0.11307755016,-24.56140350877,113.15789473684,244.59613196814],"formatted":["215","0.1 %","-24.6 %","113.16","244.60"],"year":"2015","type":"2015"},{"feature":null,"area":"carterton","values":[190,0.10211485233,-11.62790697674,100,213.24354657687],"formatted":["190","0.1 %","-11.6 %","100.00","213.24"],"year":"2016","type":"2016"}],"transforms":["original","national-percentage","annual-rate","indexed","percapita"],"id":"tertiary-qualification-completions-by-level-domestic-margin-carterton","slice":"tertiary-qualification-completions-by-level-domestic-margin"}}