{"rawdatum":{"values":[{"feature":null,"area":"horowhenua","values":[2585,0.46852202597,null,100,833.87096774193],"formatted":["2,585","0.5 %",null,"100.00","833.87"],"year":"2011","type":"2011"},{"feature":null,"area":"horowhenua","values":[2580,0.47652029366,-0.19342359767,99.80657640232,826.923076],"formatted":["2,580","0.5 %","-0.2 %","99.81","826.92"],"year":"2012","type":"2012"},{"feature":null,"area":"horowhenua","values":[2490,0.47101997578,-3.48837209302,96.3249516441,798.076923],"formatted":["2,490","0.5 %","-3.5 %","96.32","798.08"],"year":"2013","type":"2013"},{"feature":null,"area":"horowhenua","values":[2445,0.46493938673,-1.80722891566,94.58413926499,781.1501597444],"formatted":["2,445","0.5 %","-1.8 %","94.58","781.15"],"year":"2014","type":"2014"},{"feature":null,"area":"horowhenua","values":[2385,0.45195705934,-2.45398773006,92.26305609284,759.55414012738],"formatted":["2,385","0.5 %","-2.5 %","92.26","759.55"],"year":"2015","type":"2015"},{"feature":null,"area":"horowhenua","values":[2360,0.45274476513,-1.04821802935,91.29593810444,739.8119122257],"formatted":["2,360","0.5 %","-1.0 %","91.30","739.81"],"year":"2016","type":"2016"},{"feature":null,"area":"horowhenua","values":[2395,0.47518898434,1.48305084745,92.6499032882,736.923076],"formatted":["2,395","0.5 %","1.5 %","92.65","736.92"],"year":"2017","type":"2017"}],"transforms":["original","national-percentage","annual-rate","indexed","percapita"],"id":"tertiary-enrolments-by-age-domestic-margin-horowhenua","slice":"tertiary-enrolments-by-age-domestic-margin"}}