{"rawdatum":{"values":[{"feature":"under-21-years","area":"hurunui","values":[135,9.492335817e-2,null,100,116.883116,18.12080536912],"formatted":["135","0.1 %",null,"100.00","116.88","18.1 %"],"year":"2011","type":"2011"},{"feature":"under-21-years","area":"hurunui","values":[145,0.10337575303,7.407,107.407,122.8813559322,17.46987951807],"formatted":["145","0.1 %","7.4 %","107.41","122.88","17.5 %"],"year":"2012","type":"2012"},{"feature":"under-21-years","area":"hurunui","values":[160,0.11259676284,10.3448275862,118.518,133.3,18.9349112426],"formatted":["160","0.1 %","10.3 %","118.52","133.33","18.9 %"],"year":"2013","type":"2013"},{"feature":"under-21-years","area":"hurunui","values":[170,0.11727777586,6.25,125.925,139.34426229508,17.61658031088],"formatted":["170","0.1 %","6.3 %","125.93","139.34","17.6 %"],"year":"2014","type":"2014"},{"feature":"under-21-years","area":"hurunui","values":[160,0.11339073739,-5.88235294117,118.518,128,16.75392670157],"formatted":["160","0.1 %","-5.9 %","118.52","128.00","16.8 %"],"year":"2015","type":"2015"},{"feature":"under-21-years","area":"hurunui","values":[140,0.10210407322,-12.5,103.703,110.23622047244,16.37426900584],"formatted":["140","0.1 %","-12.5 %","103.70","110.24","16.4 %"],"year":"2016","type":"2016"},{"feature":"under-21-years","area":"hurunui","values":[155,0.1168973189,10.714285,114.814,121.09375,19.62025316455],"formatted":["155","0.1 %","10.7 %","114.81","121.09","19.6 %"],"year":"2017","type":"2017"}],"transforms":["original","national-percentage","annual-rate","indexed","percapita","feature-percentage"],"id":"tertiary-enrolments-by-age-domestic-hurunui-under-21-years","slice":"tertiary-enrolments-by-age-domestic"}}