{"rawdatum":{"values":[{"feature":null,"area":"central-otago","values":[475,0.14488112122,null,100,261.70798898071],"formatted":["475","0.1 %",null,"100.00","261.71"],"year":"2011","type":"2011"},{"feature":null,"area":"central-otago","values":[450,0.13790778566,-5.26315789473,94.73684210526,247.252747],"formatted":["450","0.1 %","-5.3 %","94.74","247.25"],"year":"2012","type":"2012"},{"feature":null,"area":"central-otago","values":[480,0.14751982297,6.6,101.05263157894,259.459],"formatted":["480","0.1 %","6.7 %","101.05","259.46"],"year":"2013","type":"2013"},{"feature":null,"area":"central-otago","values":[490,0.15148704631,2.083,103.15789473684,259.94694960212],"formatted":["490","0.2 %","2.1 %","103.16","259.95"],"year":"2014","type":"2014"},{"feature":null,"area":"central-otago","values":[520,0.15934545788,6.12244897959,109.47368421052,270.83],"formatted":["520","0.2 %","6.1 %","109.47","270.83"],"year":"2015","type":"2015"},{"feature":null,"area":"central-otago","values":[565,0.17354711881,8.6538461,118.94736842105,286.80203045685],"formatted":["565","0.2 %","8.7 %","118.95","286.80"],"year":"2016","type":"2016"},{"feature":null,"area":"central-otago","values":[520,0.16373053731,-7.96460176991,109.47368421052,256.15763546798],"formatted":["520","0.2 %","-8.0 %","109.47","256.16"],"year":"2017","type":"2017"}],"transforms":["original","national-percentage","annual-rate","indexed","percapita"],"id":"tertiary-provision-by-provider-margin-central-otago","slice":"tertiary-provision-by-provider-margin"}}