{"rawdatum":{"values":[{"feature":"other","area":"palmerston-north","values":[455,2.72863568215,null,100,54.95169082125,3.7979966611],"formatted":["455","2.7 %",null,"100.00","54.95","3.8 %"],"year":"2011","type":"2011"},{"feature":"other","area":"palmerston-north","values":[465,2.992277,2.197802,102.197802,55.82232893157,3.703],"formatted":["465","3.0 %","2.2 %","102.20","55.82","3.7 %"],"year":"2012","type":"2012"},{"feature":"other","area":"palmerston-north","values":[445,3.0881332408,-4.30107526881,97.802197,53.29341317365,3.5233570863],"formatted":["445","3.1 %","-4.3 %","97.80","53.29","3.5 %"],"year":"2013","type":"2013"},{"feature":"other","area":"palmerston-north","values":[360,2.69865067466,-19.1011235955,79.120879,42.65402843601,3.01129234629],"formatted":["360","2.7 %","-19.1 %","79.12","42.65","3.0 %"],"year":"2014","type":"2014"},{"feature":"other","area":"palmerston-north","values":[330,2.54531430775,-8.3,72.527472,38.59649122807,2.73631840796],"formatted":["330","2.5 %","-8.3 %","72.53","38.60","2.7 %"],"year":"2015","type":"2015"},{"feature":"other","area":"palmerston-north","values":[360,2.90088638195,9.09,79.120879,41.71494785631,3.02140159462],"formatted":["360","2.9 %","9.1 %","79.12","41.71","3.0 %"],"year":"2016","type":"2016"},{"feature":"other","area":"palmerston-north","values":[275,2.31871838111,-23.61,60.43956,31.50057273768,2.4368630926],"formatted":["275","2.3 %","-23.6 %","60.44","31.50","2.4 %"],"year":"2017","type":"2017"}],"transforms":["original","national-percentage","annual-rate","indexed","percapita","feature-percentage"],"id":"tertiary-enrolments-by-ethnicity-domestic-palmerston-north-other","slice":"tertiary-enrolments-by-ethnicity-domestic"}}