{"chartdatum":{"id":"quarterly-turnover-rate-annual-average-worker-turnover-rate-by-industry-2004-health-care-and-social-assistance-absolute","values":{"Ashburton":["ashburton",[["11.8 %",11.836025]]],"Auckland":["auckland",[["13.3 %",13.282867]]],"Bay of Plenty":["bay-of-plenty",[["13.9 %",13.875]]],"Buller":["buller",[["13.3 %",13.265355]]],"Canterbury":["canterbury",[["12.0 %",12.0]]],"Carterton":["carterton",[["11.1 %",11.062053]]],"Central Hawke's Bay":["central-hawkes-bay",[["15.3 %",15.324148]]],"Central Otago":["central-otago",[["16.8 %",16.768031]]],"Christchurch":["christchurch",[["11.9 %",11.874152]]],"Clutha":["clutha",[["15.0 %",15.010533]]],"Dunedin":["dunedin",[["12.1 %",12.101123]]],"Far North":["far-north",[["16.4 %",16.419122]]],"Gisborne":["gisborne",[["11.7 %",11.675]]],"Gore":["gore",[["14.7 %",14.73798]]],"Grey":["grey",[["10.8 %",10.791343]]],"Hamilton":["hamilton",[["12.0 %",11.978039]]],"Hastings":["hastings",[["12.0 %",11.968095]]],"Hauraki":["hauraki",[["10.8 %",10.765515]]],"Hawke's Bay":["hawkes-bay",[["13.2 %",13.2]]],"Horowhenua":["horowhenua",[["13.4 %",13.37157]]],"Hurunui":["hurunui",[["21.8 %",21.780214]]],"Invercargill":["invercargill",[["12.1 %",12.056871]]],"Kaikoura":["kaikoura",[["19.2 %",19.208194]]],"Kaipara":["kaipara",[["14.3 %",14.274953]]],"Kapiti Coast":["kapiti-coast",[["15.9 %",15.886467]]],"Kawerau":["kawerau",[["12.8 %",12.791382]]],"Lower Hutt":["lower-hutt",[["12.0 %",11.997506]]],"Manawatu":["manawatu",[["15.2 %",15.243902]]],"Manawatu-Wanganui":["manawatu-wanganui",[["11.8 %",11.85]]],"Marlborough":["marlborough",[["14.5 %",14.458701]]],"Masterton":["masterton",[["11.2 %",11.249042]]],"Matamata-Piako":["matamata-piako",[["12.3 %",12.27064]]],"Napier":["napier",[["15.1 %",15.108466]]],"Nelson":["nelson",[["15.2 %",15.213406]]],"New Plymouth":["new-plymouth",[["13.2 %",13.243204]]],"New Zealand":["new-zealand",[["12.9 %",12.95]]],"Northland":["northland",[["13.7 %",13.675]]],"Opotiki":["opotiki",[["12.5 %",12.497418]]],"Otago":["otago",[["12.9 %",12.9]]],"Otorohanga":["otorohanga",[["9.7 %",9.669636]]],"Palmerston North":["palmerston-north",[["11.4 %",11.355914]]],"Porirua":["porirua",[["13.7 %",13.670053]]],"Queenstown-Lakes":["queenstown-lakes",[["19.9 %",19.931381]]],"Rangitikei":["rangitikei",[["10.9 %",10.884203]]],"Rotorua":["rotorua",[["12.1 %",12.058321]]],"Ruapehu":["ruapehu",[["14.2 %",14.164047]]],"Selwyn":["selwyn",[["12.6 %",12.632388]]],"South Taranaki":["south-taranaki",[["12.0 %",12.028259]]],"South Waikato":["south-waikato",[["12.3 %",12.332275]]],"South Wairarapa":["south-wairarapa",[["12.9 %",12.916511]]],"Southland":["southland",[["12.6 %",12.55]]],"Southland district":["southland-district",[["14.4 %",14.363681]]],"Stratford":["stratford",[["12.3 %",12.296428]]],"Taranaki":["taranaki",[["13.0 %",13.025]]],"Tararua":["tararua",[["15.0 %",14.985244]]],"Tasman":["tasman",[["15.0 %",14.99538]]],"Taupo":["taupo",[["13.9 %",13.866349]]],"Tauranga":["tauranga",[["14.6 %",14.551142]]],"Thames-Coromandel":["thames-coromandel",[["11.8 %",11.829818]]],"Timaru":["timaru",[["11.2 %",11.247379]]],"Upper Hutt":["upper-hutt",[["13.9 %",13.884225]]],"Waikato":["waikato",[["12.6 %",12.55]]],"Waikato district":["waikato-district",[["20.0 %",19.969709]]],"Waimakariri":["waimakariri",[["15.2 %",15.195048]]],"Waimate":["waimate",[["13.0 %",12.991642]]],"Waipa":["waipa",[["14.0 %",13.999012]]],"Wairoa":["wairoa",[["14.4 %",14.369263]]],"Waitaki":["waitaki",[["13.7 %",13.733225]]],"Waitomo":["waitomo",[["13.9 %",13.929114]]],"Wanganui":["wanganui",[["11.0 %",10.954505]]],"Wellington":["wellington",[["13.1 %",13.125]]],"Wellington city":["wellington-city",[["13.4 %",13.392145]]],"West Coast":["west-coast",[["14.3 %",14.25]]],"Western Bay of Plenty":["western-bay-of-plenty",[["17.4 %",17.387808]]],"Westland":["westland",[["12.8 %",12.797583]]],"Whakatane":["whakatane",[["13.5 %",13.493793]]],"Whangarei":["whangarei",[["12.3 %",12.330594]]]}}}